{
  "dates_seen": [
    "2024-07-01"
  ],
  "last_full_data": {
    "A": 7,
    "B": 7,
    "C": 2,
    "CALLSIGN": "OP2209",
    "COG": 316.4,
    "D": 2,
    "DEST": "AMSTERDAM",
    "DRAUGHT": 1.5,
    "ETA": "08-01 13:04",
    "HEADING": 511,
    "IMO": 0,
    "LATITUDE": 51.48769,
    "LONGITUDE": -0.02297,
    "MMSI": 205220930,
    "NAME": "HARABATO",
    "NAVSTAT": 15,
    "PAC": 0,
    "ROT": 128,
    "SOG": 5.9,
    "TIME": "2024-07-01 07:21:38 GMT",
    "TYPE": 36,
    "last_seen": null,
    "received_by_stations": [
      2115,
      2648
    ]
  },
  "last_seen": "2024-07-01T07:21:55.019727"
}