{
  "dates_seen": [
    "2024-07-31"
  ],
  "last_full_data": {
    "A": 17,
    "B": 0,
    "C": 0,
    "CALLSIGN": "OQ3657",
    "COG": 277.7,
    "D": 4,
    "DEST": "",
    "DRAUGHT": 0,
    "ETA": "00-00 00:00",
    "HEADING": 90,
    "IMO": 0,
    "LATITUDE": 51.50547,
    "LONGITUDE": -0.0732,
    "MMSI": 205365770,
    "NAME": "WE LL SEA",
    "NAVSTAT": 15,
    "PAC": 1,
    "ROT": 128,
    "SOG": 2.3,
    "TIME": "2024-07-31 09:24:09 GMT",
    "TYPE": 37,
    "last_seen": "2024-07-31T08:25:06.492850",
    "received_by_stations": []
  },
  "last_seen": "2024-07-31T09:25:26.077490"
}