{
  "dates_seen": [
    "2025-06-12"
  ],
  "last_full_data": {
    "A": 0,
    "B": 0,
    "C": 0,
    "CALLSIGN": "OQ5109",
    "COG": 360,
    "D": 0,
    "DEST": "",
    "DRAUGHT": 0,
    "ETA": "00-00 00:00",
    "HEADING": 511,
    "IMO": 0,
    "LATITUDE": 51.50612,
    "LONGITUDE": -0.07228,
    "MMSI": 205510970,
    "NAME": "POLLEN",
    "NAVSTAT": 15,
    "PAC": 0,
    "ROT": 128,
    "SOG": 0,
    "TIME": "2025-06-12 13:25:22 GMT",
    "TYPE": 36,
    "last_seen": "2025-06-12T12:57:37.755097",
    "received_by_stations": []
  },
  "last_seen": "2025-06-12T13:41:01.436898"
}