{
  "dates_seen": [
    "2025-09-08",
    "2025-09-09",
    "2025-09-10"
  ],
  "last_full_data": {
    "A": 59,
    "B": 84,
    "C": 9,
    "CALLSIGN": "DRAA",
    "COG": 92.3,
    "D": 8,
    "DEST": "0",
    "DRAUGHT": 6.6,
    "ETA": "00-00 24:60",
    "HEADING": 92,
    "IMO": 0,
    "LATITUDE": 51.50687,
    "LONGITUDE": 0.02828,
    "MMSI": 211210150,
    "NAME": "GERMAN WARSHIP F219",
    "NAVSTAT": 5,
    "PAC": 0,
    "ROT": 0,
    "SOG": 0,
    "TIME": "2025-09-10 22:24:50 GMT",
    "TYPE": 35,
    "last_seen": "2025-09-10T21:23:38.211725",
    "received_by_stations": []
  },
  "last_seen": "2025-09-10T22:27:28.908979"
}