{
  "dates_seen": [
    "2025-06-14",
    "2025-06-15",
    "2025-06-16"
  ],
  "last_full_data": {
    "A": 6,
    "B": 4,
    "C": 2,
    "CALLSIGN": "DJ3289",
    "COG": 109.4,
    "D": 2,
    "DEST": "",
    "DRAUGHT": 0,
    "ETA": "00-00 00:00",
    "HEADING": 511,
    "IMO": 0,
    "LATITUDE": 51.49608,
    "LONGITUDE": 0.02217,
    "MMSI": 211826640,
    "NAME": "DULCINEA",
    "NAVSTAT": 15,
    "PAC": 1,
    "ROT": 128,
    "SOG": 8.4,
    "TIME": "2025-06-16 06:14:12 GMT",
    "TYPE": 36,
    "last_seen": "2025-06-16T05:33:43.679218",
    "received_by_stations": []
  },
  "last_seen": "2025-06-16T06:44:41.846573"
}