{
  "dates_seen": [
    "2025-07-05"
  ],
  "last_full_data": {
    "A": 16,
    "B": 16,
    "C": 3,
    "CALLSIGN": "FYAR",
    "COG": 185.8,
    "D": 3,
    "DEST": "",
    "DRAUGHT": 2.2,
    "ETA": "00-00 24:60",
    "HEADING": 300,
    "IMO": 0,
    "LATITUDE": 51.50494,
    "LONGITUDE": -0.07132,
    "MMSI": 228867700,
    "NAME": "FRENCH WARSHIP ARM",
    "NAVSTAT": 0,
    "PAC": 0,
    "ROT": 0,
    "SOG": 0,
    "TIME": "2025-07-05 21:26:27 GMT",
    "TYPE": 35,
    "last_seen": "2025-07-05T20:28:51.984483",
    "received_by_stations": []
  },
  "last_seen": "2025-07-05T21:26:32.687610"
}