{
  "dates_seen": [
    "2024-06-25",
    "2024-06-26",
    "2024-06-27",
    "2024-06-28",
    "2024-06-29",
    "2024-07-04",
    "2024-07-06",
    "2024-07-11"
  ],
  "last_full_data": {
    "A": 81,
    "B": 9,
    "C": 11,
    "CALLSIGN": "MPEH5",
    "COG": 360,
    "D": 4,
    "DEST": "DELFZIJL",
    "DRAUGHT": 0,
    "ETA": "00-00 24:60",
    "HEADING": 511,
    "IMO": 9963267,
    "LATITUDE": 51.50889,
    "LONGITUDE": -0.11906,
    "MMSI": 232054955,
    "NAME": "SCOT LEADER",
    "NAVSTAT": 0,
    "PAC": 1,
    "ROT": 128,
    "SOG": 0,
    "TIME": "2024-07-11 12:42:25 GMT",
    "TYPE": 70,
    "last_seen": "2024-07-11T11:20:42.379534",
    "received_by_stations": []
  },
  "last_seen": "2024-07-11T12:43:05.390514"
}