{
  "dates_seen": [
    "2024-06-24",
    "2024-06-26",
    "2024-07-11"
  ],
  "last_full_data": {
    "A": 7,
    "B": 11,
    "C": 3,
    "CALLSIGN": "MDVO7",
    "COG": 23.9,
    "D": 2,
    "DEST": "WORKING RIVER THAMES",
    "DRAUGHT": 2.2,
    "ETA": "05-10 00:00",
    "HEADING": 511,
    "IMO": 0,
    "LATITUDE": 51.50788,
    "LONGITUDE": -0.0815,
    "MMSI": 232017999,
    "NAME": "IRENE",
    "NAVSTAT": 0,
    "PAC": 0,
    "ROT": 128,
    "SOG": 0.1,
    "TIME": "2024-07-11 11:12:42 GMT",
    "TYPE": 52,
    "last_seen": "2024-07-11T10:26:48.954295",
    "received_by_stations": []
  },
  "last_seen": "2024-07-11T11:20:42.383076"
}