{
  "dates_seen": [
    "2024-06-25",
    "2024-06-26",
    "2024-06-27",
    "2024-06-28"
  ],
  "last_full_data": {
    "A": 0,
    "B": 0,
    "C": 0,
    "CALLSIGN": "MPEH5",
    "COG": 360,
    "D": 0,
    "DEST": "DELFZIJL",
    "DRAUGHT": 0,
    "ETA": "00-00 24:60",
    "HEADING": 511,
    "IMO": 9963267,
    "LATITUDE": 51.50889,
    "LONGITUDE": -0.11904,
    "MMSI": 232054955,
    "NAME": "SCOT LEADER",
    "NAVSTAT": 0,
    "PAC": 1,
    "ROT": 128,
    "SOG": 0.1,
    "TIME": "2024-06-28 13:24:01 GMT",
    "TYPE": 0,
    "last_seen": "2024-06-28T12:41:28.687382",
    "received_by_stations": []
  },
  "last_seen": "2024-06-28T13:24:04.679034"
}