{
  "dates_seen": [
    "2025-06-26",
    "2025-06-28"
  ],
  "last_full_data": {
    "A": 12,
    "B": 10,
    "C": 3,
    "CALLSIGN": "MJKJ8",
    "COG": 299.7,
    "D": 2,
    "DEST": "",
    "DRAUGHT": 0,
    "ETA": "00-00 00:00",
    "HEADING": 286,
    "IMO": 0,
    "LATITUDE": 51.50694,
    "LONGITUDE": -0.07909,
    "MMSI": 232036567,
    "NAME": "SY VIVEKA",
    "NAVSTAT": 15,
    "PAC": 1,
    "ROT": 128,
    "SOG": 4.2,
    "TIME": "2025-06-28 14:28:04 GMT",
    "TYPE": 37,
    "last_seen": "2025-06-28T13:34:26.500908",
    "received_by_stations": []
  },
  "last_seen": "2025-06-28T14:28:21.439661"
}