{
  "dates_seen": [
    "2025-09-15",
    "2025-09-16",
    "2025-09-17"
  ],
  "last_full_data": {
    "A": 8,
    "B": 4,
    "C": 2,
    "CALLSIGN": "MORD5",
    "COG": 70.6,
    "D": 2,
    "DEST": "PORT OF ROTTERDAM",
    "DRAUGHT": 2.4,
    "ETA": "05-15 14:00",
    "HEADING": 142,
    "IMO": 1024687,
    "LATITUDE": 51.50604,
    "LONGITUDE": -0.07355,
    "MMSI": 232052642,
    "NAME": "ARTEMIS EF12-001",
    "NAVSTAT": 5,
    "PAC": 1,
    "ROT": 14,
    "SOG": 0.1,
    "TIME": "2025-09-17 15:27:18 GMT",
    "TYPE": 37,
    "last_seen": "2025-09-17T14:29:05.643170",
    "received_by_stations": []
  },
  "last_seen": "2025-09-17T15:28:14.452498"
}