{
  "dates_seen": [
    "2024-06-25",
    "2024-06-26",
    "2024-06-27",
    "2024-06-28",
    "2024-06-30",
    "2024-07-02",
    "2024-07-14",
    "2024-07-23",
    "2024-07-25",
    "2024-07-28",
    "2024-07-30",
    "2024-08-07",
    "2024-08-11",
    "2024-08-19",
    "2024-08-24",
    "2024-08-26",
    "2024-08-28"
  ],
  "last_full_data": {
    "A": 16,
    "B": 16,
    "C": 5,
    "CALLSIGN": "MOEN3",
    "COG": 169.4,
    "D": 7,
    "DEST": "HARBOUR TOWAGE",
    "DRAUGHT": 6.2,
    "ETA": "05-29 18:00",
    "HEADING": 349,
    "IMO": 0,
    "LATITUDE": 51.49137,
    "LONGITUDE": -0.00019,
    "MMSI": 232049867,
    "NAME": "VB PETER",
    "NAVSTAT": 0,
    "PAC": 1,
    "ROT": 127,
    "SOG": 3.6,
    "TIME": "2024-08-28 06:31:57 GMT",
    "TYPE": 52,
    "last_seen": "2024-08-26T17:24:41.679591",
    "received_by_stations": []
  },
  "last_seen": "2024-08-28T06:32:01.544629"
}