{
  "dates_seen": [
    "2024-06-25",
    "2024-06-26",
    "2024-06-27"
  ],
  "last_full_data": {
    "A": 19,
    "B": 19,
    "C": 7,
    "CALLSIGN": "MMCS9",
    "COG": 298.7,
    "D": 1,
    "DEST": "LONDON",
    "DRAUGHT": 1.2,
    "ETA": "00-00 24:60",
    "HEADING": 293,
    "IMO": 9963499,
    "LATITUDE": 51.50443,
    "LONGITUDE": -0.07131,
    "MMSI": 232043461,
    "NAME": "EARTH CLIPPER",
    "NAVSTAT": 0,
    "PAC": 0,
    "ROT": 0,
    "SOG": 9.8,
    "TIME": "2024-06-27 22:24:11 GMT",
    "TYPE": 40,
    "last_seen": "2024-06-27T21:20:51.172929",
    "received_by_stations": []
  },
  "last_seen": "2024-06-27T22:24:16.704772"
}