{
  "dates_seen": [
    "2026-03-20",
    "2026-03-27",
    "2026-04-10",
    "2026-04-20",
    "2026-04-22",
    "2026-04-24",
    "2026-05-10",
    "2026-05-14",
    "2026-05-16",
    "2026-05-17",
    "2026-05-21",
    "2026-05-24",
    "2026-05-30",
    "2026-05-31",
    "2026-06-02",
    "2026-06-06",
    "2026-06-07"
  ],
  "last_full_data": {
    "A": 0,
    "B": 0,
    "C": 0,
    "CALLSIGN": "MTEQ8",
    "COG": 218.4,
    "D": 0,
    "DEST": "",
    "DRAUGHT": 0,
    "ETA": "00-00 00:00",
    "HEADING": 511,
    "IMO": 0,
    "LATITUDE": 51.48886,
    "LONGITUDE": -0.02817,
    "MMSI": 232065333,
    "NAME": "AMR VIPER",
    "NAVSTAT": 15,
    "PAC": 1,
    "ROT": 128,
    "SOG": 0.6,
    "TIME": "2026-06-07 09:15:17 GMT",
    "TYPE": 40,
    "last_seen": "2026-06-06T13:45:36.682160",
    "received_by_stations": []
  },
  "last_seen": "2026-06-07T09:15:21.535920"
}