{
  "dates_seen": [
    "2025-04-23",
    "2025-04-24",
    "2025-04-25",
    "2025-04-29",
    "2025-06-13",
    "2025-06-14",
    "2025-06-17"
  ],
  "last_full_data": {
    "A": 12,
    "B": 0,
    "C": 0,
    "CALLSIGN": "MORL9",
    "COG": 100.6,
    "D": 4,
    "DEST": "",
    "DRAUGHT": 0,
    "ETA": "00-00 24:60",
    "HEADING": 16,
    "IMO": 0,
    "LATITUDE": 51.50822,
    "LONGITUDE": -0.0381,
    "MMSI": 232052714,
    "NAME": "HURRICANE 1",
    "NAVSTAT": 0,
    "PAC": 1,
    "ROT": 80,
    "SOG": 47.2,
    "TIME": "2025-06-17 12:58:38 GMT",
    "TYPE": 55,
    "last_seen": "2025-06-14T15:27:11.658070",
    "received_by_stations": []
  },
  "last_seen": "2025-06-17T12:58:50.646268"
}