{
  "dates_seen": [
    "2025-01-21",
    "2025-01-22"
  ],
  "last_full_data": {
    "A": 15,
    "B": 1,
    "C": 1,
    "CALLSIGN": "MPJA3",
    "COG": 282.7,
    "D": 4,
    "DEST": "COWES",
    "DRAUGHT": 0,
    "ETA": "08-07 17:00",
    "HEADING": 282,
    "IMO": 0,
    "LATITUDE": 51.50948,
    "LONGITUDE": -0.09454,
    "MMSI": 232055511,
    "NAME": "ROCKET REBEL",
    "NAVSTAT": 9,
    "PAC": 0,
    "ROT": -35,
    "SOG": 9.4,
    "TIME": "2025-01-22 13:28:39 GMT",
    "TYPE": 40,
    "last_seen": "2025-01-22T12:48:08.277612",
    "received_by_stations": []
  },
  "last_seen": "2025-01-22T13:28:39.491122"
}