{
  "dates_seen": [
    "2024-06-24",
    "2024-06-26"
  ],
  "last_full_data": {
    "A": 10,
    "B": 6,
    "C": 2,
    "CALLSIGN": "MFAQ5",
    "COG": 265,
    "D": 1,
    "DEST": "TBW",
    "DRAUGHT": 0.6,
    "ETA": "00-00 24:60",
    "HEADING": 511,
    "IMO": 0,
    "LATITUDE": 51.50741,
    "LONGITUDE": 0.00717,
    "MMSI": 232022992,
    "NAME": "COMET CLIPPER",
    "NAVSTAT": 0,
    "PAC": 1,
    "ROT": 128,
    "SOG": 0.1,
    "TIME": "2024-06-26 11:19:25 GMT",
    "TYPE": 56,
    "last_seen": "2024-06-24T11:17:36.490545",
    "received_by_stations": []
  },
  "last_seen": "2024-06-26T11:19:34.690516"
}