{
  "dates_seen": [
    "2024-06-22",
    "2024-06-28",
    "2024-06-29",
    "2024-07-02",
    "2024-07-03",
    "2024-07-04",
    "2024-07-05",
    "2024-07-06",
    "2024-07-07",
    "2024-07-08",
    "2024-07-10",
    "2024-07-11"
  ],
  "last_full_data": {
    "A": 8,
    "B": 91,
    "C": 16,
    "CALLSIGN": "MLLN8",
    "COG": 262.7,
    "D": 1,
    "DEST": "CHARLTON",
    "DRAUGHT": 4.4,
    "ETA": "07-11 03:00",
    "HEADING": 256,
    "IMO": 8902278,
    "LATITUDE": 51.49714,
    "LONGITUDE": 0.03282,
    "MMSI": 232000790,
    "NAME": "CITY OF WESTMINSTER",
    "NAVSTAT": 0,
    "PAC": 0,
    "ROT": 0,
    "SOG": 4.4,
    "TIME": "2024-07-11 01:38:10 GMT",
    "TYPE": 33,
    "last_seen": "2024-07-10T08:28:34.602107",
    "received_by_stations": []
  },
  "last_seen": "2024-07-11T01:38:20.533506"
}