{
  "dates_seen": [
    "2024-06-25",
    "2024-06-26",
    "2024-06-27",
    "2024-06-28"
  ],
  "last_full_data": {
    "A": 13,
    "B": 3,
    "C": 0,
    "CALLSIGN": "MLPR8",
    "COG": 342,
    "D": 5,
    "DEST": "",
    "DRAUGHT": 0,
    "ETA": "00-00 24:60",
    "HEADING": 117,
    "IMO": 0,
    "LATITUDE": 51.505,
    "LONGITUDE": -0.07092,
    "MMSI": 232042335,
    "NAME": "ERRINGTON",
    "NAVSTAT": 15,
    "PAC": 1,
    "ROT": -9,
    "SOG": 0,
    "TIME": "2024-06-28 23:22:36 GMT",
    "TYPE": 51,
    "last_seen": "2024-06-28T22:24:44.123868",
    "received_by_stations": []
  },
  "last_seen": "2024-06-28T23:22:42.113682"
}