{
  "dates_seen": [
    "2025-05-16",
    "2025-05-17",
    "2025-05-31",
    "2025-06-01",
    "2025-08-30",
    "2025-08-31",
    "2025-09-01",
    "2025-09-02",
    "2025-09-03"
  ],
  "last_full_data": {
    "A": 6,
    "B": 7,
    "C": 2,
    "CALLSIGN": "MSBP3",
    "COG": 360,
    "D": 1,
    "DEST": "",
    "DRAUGHT": 0,
    "ETA": "00-00 00:00",
    "HEADING": 511,
    "IMO": 0,
    "LATITUDE": 51.50705,
    "LONGITUDE": -0.07139,
    "MMSI": 232061108,
    "NAME": "GAY VENTURE",
    "NAVSTAT": 15,
    "PAC": 1,
    "ROT": 128,
    "SOG": 0,
    "TIME": "2025-09-03 07:23:23 GMT",
    "TYPE": 37,
    "last_seen": "2025-09-03T06:37:07.584316",
    "received_by_stations": []
  },
  "last_seen": "2025-09-03T07:25:29.743869"
}