{
  "dates_seen": [
    "2024-05-25",
    "2025-05-02",
    "2025-05-18"
  ],
  "last_full_data": {
    "A": 6,
    "B": 6,
    "C": 1,
    "CALLSIGN": "2OSK",
    "COG": 261.2,
    "D": 3,
    "DEST": "",
    "DRAUGHT": 0,
    "ETA": "00-00 00:00",
    "HEADING": 511,
    "IMO": 0,
    "LATITUDE": 51.48435,
    "LONGITUDE": -0.14962,
    "MMSI": 235057325,
    "NAME": "CANTARA OF DART",
    "NAVSTAT": 15,
    "PAC": 1,
    "ROT": 128,
    "SOG": 7.1,
    "TIME": "2025-05-18 12:51:09 GMT",
    "TYPE": 37,
    "last_seen": "2025-05-02T07:26:26.359839",
    "received_by_stations": []
  },
  "last_seen": "2025-05-18T12:51:11.522489"
}