{
  "dates_seen": [
    "2024-06-20",
    "2024-07-05",
    "2024-12-17"
  ],
  "last_full_data": {
    "A": 5,
    "B": 4,
    "C": 1,
    "CALLSIGN": "MDYD9",
    "COG": 324.6,
    "D": 3,
    "DEST": "LONDON",
    "DRAUGHT": 1,
    "ETA": "12-17 15:30",
    "HEADING": 511,
    "IMO": 0,
    "LATITUDE": 51.50503,
    "LONGITUDE": 0.01004,
    "MMSI": 235001996,
    "NAME": "PREDATOR 3",
    "NAVSTAT": 11,
    "PAC": 1,
    "ROT": 128,
    "SOG": 8.1,
    "TIME": "2024-12-17 13:31:17 GMT",
    "TYPE": 60,
    "last_seen": "2024-07-05T17:24:17.198196",
    "received_by_stations": [
      3416,
      2103,
      2115,
      2648
    ]
  },
  "last_seen": "2024-12-17T13:35:05.857512"
}