{
  "dates_seen": [
    "2024-06-24",
    "2024-07-24",
    "2024-07-26",
    "2024-07-31",
    "2024-08-01",
    "2024-08-02",
    "2024-08-29",
    "2024-09-06",
    "2024-09-21",
    "2024-10-09",
    "2025-03-26",
    "2025-03-28",
    "2025-04-01",
    "2025-04-08",
    "2025-04-10",
    "2025-04-11",
    "2025-04-13",
    "2025-04-14",
    "2025-04-15",
    "2025-04-16",
    "2025-04-22",
    "2025-04-24",
    "2025-05-08",
    "2025-05-12",
    "2025-05-13",
    "2025-06-06",
    "2025-06-09",
    "2025-06-13",
    "2025-06-17",
    "2025-06-18",
    "2025-06-20",
    "2025-07-03",
    "2025-07-08",
    "2025-07-28",
    "2025-07-31"
  ],
  "last_full_data": {
    "A": 8,
    "B": 1,
    "C": 2,
    "CALLSIGN": "",
    "COG": 41.5,
    "D": 1,
    "DEST": "",
    "DRAUGHT": 0,
    "ETA": "00-00 24:60",
    "HEADING": 511,
    "IMO": 0,
    "LATITUDE": 51.50566,
    "LONGITUDE": -0.07841,
    "MMSI": 235094318,
    "NAME": "TYBURN",
    "NAVSTAT": 15,
    "PAC": 1,
    "ROT": 128,
    "SOG": 0,
    "TIME": "2025-07-31 09:25:44 GMT",
    "TYPE": 53,
    "last_seen": "2025-07-31T08:42:42.529829",
    "received_by_stations": []
  },
  "last_seen": "2025-07-31T09:37:20.734524"
}