{
  "dates_seen": [
    "2024-06-25",
    "2024-06-26",
    "2024-06-27"
  ],
  "last_full_data": {
    "A": 18,
    "B": 4,
    "C": 1,
    "CALLSIGN": "2AHC8",
    "COG": 270.2,
    "D": 3,
    "DEST": "",
    "DRAUGHT": 0,
    "ETA": "00-00 24:60",
    "HEADING": 511,
    "IMO": 0,
    "LATITUDE": 51.48443,
    "LONGITUDE": -0.01568,
    "MMSI": 235059592,
    "NAME": "OASIS",
    "NAVSTAT": 12,
    "PAC": 0,
    "ROT": 128,
    "SOG": 0.1,
    "TIME": "2024-06-27 07:20:14 GMT",
    "TYPE": 80,
    "last_seen": "2024-06-27T06:30:10.795558",
    "received_by_stations": []
  },
  "last_seen": "2024-06-27T07:20:14.845339"
}