{
  "dates_seen": [
    "2025-09-27",
    "2025-09-28",
    "2025-09-29"
  ],
  "last_full_data": {
    "A": 11,
    "B": 3,
    "C": 3,
    "CALLSIGN": "2CPF5",
    "COG": 360,
    "D": 2,
    "DEST": "",
    "DRAUGHT": 0,
    "ETA": "00-00 00:00",
    "HEADING": 511,
    "IMO": 0,
    "LATITUDE": 51.50671,
    "LONGITUDE": -0.07097,
    "MMSI": 235074654,
    "NAME": "WAVE OF MALDON",
    "NAVSTAT": 15,
    "PAC": 1,
    "ROT": 128,
    "SOG": 0.1,
    "TIME": "2025-09-29 04:29:56 GMT",
    "TYPE": 37,
    "last_seen": "2025-09-29T03:10:39.117400",
    "received_by_stations": []
  },
  "last_seen": "2025-09-29T04:32:33.075413"
}