{
  "dates_seen": [
    "2024-08-07",
    "2025-02-25"
  ],
  "last_full_data": {
    "A": 13,
    "B": 5,
    "C": 3,
    "CALLSIGN": "MXGQ6",
    "COG": 107.9,
    "D": 1,
    "DEST": "",
    "DRAUGHT": 0,
    "ETA": "00-00 00:00",
    "HEADING": 511,
    "IMO": 0,
    "LATITUDE": 51.50761,
    "LONGITUDE": -0.07215,
    "MMSI": 235001127,
    "NAME": "DOVELET",
    "NAVSTAT": 15,
    "PAC": 0,
    "ROT": 128,
    "SOG": 0,
    "TIME": "2025-02-25 16:20:36 GMT",
    "TYPE": 37,
    "last_seen": "2025-02-25T13:31:28.948799",
    "received_by_stations": []
  },
  "last_seen": "2025-02-25T16:33:26.464054"
}