{
  "dates_seen": [
    "2024-06-25",
    "2024-06-26"
  ],
  "last_full_data": {
    "A": 18,
    "B": 0,
    "C": 5,
    "CALLSIGN": "MNSY3",
    "COG": 248.6,
    "D": 0,
    "DEST": "LONDON",
    "DRAUGHT": 1.2,
    "ETA": "00-00 00:00",
    "HEADING": 511,
    "IMO": 0,
    "LATITUDE": 51.48644,
    "LONGITUDE": -0.29094,
    "MMSI": 235055756,
    "NAME": "COCKNEY SPARROW",
    "NAVSTAT": 0,
    "PAC": 1,
    "ROT": 128,
    "SOG": 9.4,
    "TIME": "2024-06-26 16:28:16 GMT",
    "TYPE": 99,
    "last_seen": "2024-06-26T15:24:35.091660",
    "received_by_stations": []
  },
  "last_seen": "2024-06-26T16:28:33.297336"
}