{
  "dates_seen": [
    "2024-06-21",
    "2024-06-27",
    "2024-06-30",
    "2024-07-01"
  ],
  "last_full_data": {
    "A": 0,
    "B": 0,
    "C": 0,
    "CALLSIGN": "MNQH7",
    "COG": 17.8,
    "D": 0,
    "DEST": "",
    "DRAUGHT": 18.7,
    "ETA": "00-00 00:07",
    "HEADING": 511,
    "IMO": 0,
    "LATITUDE": 51.47322,
    "LONGITUDE": -0.17911,
    "MMSI": 235094988,
    "NAME": "SILVER DARLING",
    "NAVSTAT": 15,
    "PAC": 1,
    "ROT": 128,
    "SOG": 9.3,
    "TIME": "2024-07-01 16:27:47 GMT",
    "TYPE": 0,
    "last_seen": "2024-07-01T14:24:23.525446",
    "received_by_stations": []
  },
  "last_seen": "2024-07-01T16:27:48.154268"
}