{
  "dates_seen": [
    "2025-09-20"
  ],
  "last_full_data": {
    "A": 6,
    "B": 0,
    "C": 1,
    "CALLSIGN": "MRYK2",
    "COG": 255.8,
    "D": 1,
    "DEST": "",
    "DRAUGHT": 0,
    "ETA": "00-00 00:00",
    "HEADING": 511,
    "IMO": 0,
    "LATITUDE": 51.50204,
    "LONGITUDE": -0.05837,
    "MMSI": 235055046,
    "NAME": "BISTROMATH",
    "NAVSTAT": 15,
    "PAC": 0,
    "ROT": 128,
    "SOG": 7.8,
    "TIME": "2025-09-20 10:28:17 GMT",
    "TYPE": 37,
    "last_seen": "2025-09-20T09:25:09.097588",
    "received_by_stations": []
  },
  "last_seen": "2025-09-20T10:28:42.454683"
}