{
  "dates_seen": [
    "2024-06-23",
    "2024-06-25",
    "2024-06-26",
    "2024-06-27"
  ],
  "last_full_data": {
    "A": 9,
    "B": 9,
    "C": 2,
    "CALLSIGN": "MQGB6",
    "COG": 191.5,
    "D": 2,
    "DEST": "",
    "DRAUGHT": 0,
    "ETA": "00-00 00:00",
    "HEADING": 185,
    "IMO": 0,
    "LATITUDE": 51.49124,
    "LONGITUDE": -0.12428,
    "MMSI": 235033771,
    "NAME": "SIGRID OF CHELSEA",
    "NAVSTAT": 15,
    "PAC": 1,
    "ROT": 128,
    "SOG": 10.5,
    "TIME": "2024-06-27 14:23:44 GMT",
    "TYPE": 37,
    "last_seen": "2024-06-27T13:25:17.052309",
    "received_by_stations": []
  },
  "last_seen": "2024-06-27T14:24:20.892405"
}