{
  "dates_seen": [
    "2024-01-20",
    "2025-01-29"
  ],
  "last_full_data": {
    "A": 13,
    "B": 12,
    "C": 4,
    "CALLSIGN": "ZQQQ5",
    "COG": 46.1,
    "D": 5,
    "DEST": "GREENWICH",
    "DRAUGHT": 2.4,
    "ETA": "01-23 15:00",
    "HEADING": 342,
    "IMO": 0,
    "LATITUDE": 51.49514,
    "LONGITUDE": -0.00015,
    "MMSI": 235000357,
    "NAME": "SARAH GREY",
    "NAVSTAT": 5,
    "PAC": 1,
    "ROT": 0,
    "SOG": 0,
    "TIME": "2025-01-29 11:18:40 GMT",
    "TYPE": 52,
    "last_seen": "2025-01-29T10:28:55.430189",
    "received_by_stations": []
  },
  "last_seen": "2025-01-29T11:20:39.246141"
}