{
  "dates_seen": [
    "2024-05-26",
    "2024-07-04",
    "2024-07-05",
    "2024-08-07",
    "2024-09-20",
    "2024-09-26",
    "2024-09-27",
    "2025-02-19",
    "2025-02-20"
  ],
  "last_full_data": {
    "A": 0,
    "B": 0,
    "C": 0,
    "CALLSIGN": "2JD07",
    "COG": 80.2,
    "D": 0,
    "DEST": "GREENWICH",
    "DRAUGHT": 1.8,
    "ETA": "00-00 24:60",
    "HEADING": 511,
    "IMO": 0,
    "LATITUDE": 51.51053,
    "LONGITUDE": -0.10212,
    "MMSI": 235115041,
    "NAME": "REBEL",
    "NAVSTAT": 15,
    "PAC": 0,
    "ROT": 128,
    "SOG": 5.3,
    "TIME": "2025-02-20 16:33:23 GMT",
    "TYPE": 52,
    "last_seen": "2025-02-20T15:28:17.107933",
    "received_by_stations": []
  },
  "last_seen": "2025-02-20T16:33:32.608824"
}