{
  "dates_seen": [
    "2024-06-25",
    "2024-06-26"
  ],
  "last_full_data": {
    "A": 25,
    "B": 7,
    "C": 3,
    "CALLSIGN": "2ITT4",
    "COG": 281.5,
    "D": 3,
    "DEST": "LONDON",
    "DRAUGHT": 1,
    "ETA": "00-00 00:00",
    "HEADING": 511,
    "IMO": 0,
    "LATITUDE": 51.46435,
    "LONGITUDE": -0.20241,
    "MMSI": 235112741,
    "NAME": "GALAXY CLIPPER",
    "NAVSTAT": 0,
    "PAC": 1,
    "ROT": 128,
    "SOG": 7.6,
    "TIME": "2024-06-26 20:22:01 GMT",
    "TYPE": 40,
    "last_seen": "2024-06-26T19:18:42.079151",
    "received_by_stations": []
  },
  "last_seen": "2024-06-26T20:25:50.974848"
}