{
  "dates_seen": [
    "2024-06-25",
    "2024-06-26",
    "2024-06-27",
    "2024-06-28",
    "2024-06-29"
  ],
  "last_full_data": {
    "A": 5,
    "B": 4,
    "C": 2,
    "CALLSIGN": "2HLP7",
    "COG": 219,
    "D": 2,
    "DEST": "IMPERIAL WHARF",
    "DRAUGHT": 0.6,
    "ETA": "04-13 21:30",
    "HEADING": 212,
    "IMO": 0,
    "LATITUDE": 51.48776,
    "LONGITUDE": -0.12782,
    "MMSI": 235104656,
    "NAME": "THAMES LIMO",
    "NAVSTAT": 9,
    "PAC": 0,
    "ROT": -127,
    "SOG": 4.4,
    "TIME": "2024-06-29 09:23:37 GMT",
    "TYPE": 60,
    "last_seen": "2024-06-28T17:24:31.935418",
    "received_by_stations": []
  },
  "last_seen": "2024-06-29T09:23:41.184700"
}