{
  "dates_seen": [
    "2024-06-25",
    "2024-06-26",
    "2024-06-27"
  ],
  "last_full_data": {
    "A": 0,
    "B": 0,
    "C": 0,
    "CALLSIGN": "2HPH9",
    "COG": 91.1,
    "D": 0,
    "DEST": "WATERLOO PIER",
    "DRAUGHT": 0,
    "ETA": "08-07 18:15",
    "HEADING": 511,
    "IMO": 0,
    "LATITUDE": 51.50777,
    "LONGITUDE": -0.04276,
    "MMSI": 235105516,
    "NAME": "ROCKET JUNIOR",
    "NAVSTAT": 0,
    "PAC": 1,
    "ROT": 128,
    "SOG": 27.7,
    "TIME": "2024-06-27 18:27:33 GMT",
    "TYPE": 40,
    "last_seen": "2024-06-27T17:25:16.969884",
    "received_by_stations": []
  },
  "last_seen": "2024-06-27T18:27:34.097127"
}