{
  "dates_seen": [
    "2024-06-28"
  ],
  "last_full_data": {
    "A": 12,
    "B": 1,
    "C": 4,
    "CALLSIGN": "PG4447",
    "COG": 360,
    "D": 1,
    "DEST": "",
    "DRAUGHT": 0,
    "ETA": "00-00 00:00",
    "HEADING": 511,
    "IMO": 0,
    "LATITUDE": 51.50772,
    "LONGITUDE": -0.07222,
    "MMSI": 244001949,
    "NAME": "AVALON",
    "NAVSTAT": 15,
    "PAC": 1,
    "ROT": 128,
    "SOG": 0.1,
    "TIME": "2024-06-28 18:02:10 GMT",
    "TYPE": 36,
    "last_seen": "2024-06-28T17:24:31.944245",
    "received_by_stations": []
  },
  "last_seen": "2024-06-28T18:28:42.363008"
}