{
  "dates_seen": [
    "2025-04-10",
    "2025-04-11",
    "2025-04-12",
    "2025-04-13"
  ],
  "last_full_data": {
    "A": 9,
    "B": 2,
    "C": 3,
    "CALLSIGN": "PC4293",
    "COG": 359.2,
    "D": 1,
    "DEST": "",
    "DRAUGHT": 0,
    "ETA": "00-00 24:60",
    "HEADING": 511,
    "IMO": 0,
    "LATITUDE": 51.49243,
    "LONGITUDE": -0.00029,
    "MMSI": 244260617,
    "NAME": "NAJADE",
    "NAVSTAT": 15,
    "PAC": 0,
    "ROT": 128,
    "SOG": 5.2,
    "TIME": "2025-04-13 13:33:00 GMT",
    "TYPE": 37,
    "last_seen": "2025-04-13T12:48:29.236222",
    "received_by_stations": []
  },
  "last_seen": "2025-04-13T13:33:09.646382"
}