{
  "dates_seen": [
    "2025-08-21"
  ],
  "last_full_data": {
    "A": 11,
    "B": 1,
    "C": 2,
    "CALLSIGN": "PA2632",
    "COG": 219.8,
    "D": 2,
    "DEST": "AMSTERDAM",
    "DRAUGHT": 0,
    "ETA": "08-30 06:00",
    "HEADING": 511,
    "IMO": 0,
    "LATITUDE": 51.50812,
    "LONGITUDE": -0.07272,
    "MMSI": 244564436,
    "NAME": "BEAGLE",
    "NAVSTAT": 15,
    "PAC": 1,
    "ROT": 128,
    "SOG": 0.3,
    "TIME": "2025-08-21 13:35:19 GMT",
    "TYPE": 37,
    "last_seen": "2025-08-21T12:56:33.163812",
    "received_by_stations": []
  },
  "last_seen": "2025-08-21T13:37:23.566269"
}