{
  "dates_seen": [
    "2024-08-19",
    "2024-08-23"
  ],
  "last_full_data": {
    "A": 9,
    "B": 2,
    "C": 2,
    "CALLSIGN": "PE5757",
    "COG": 360,
    "D": 2,
    "DEST": "",
    "DRAUGHT": 0,
    "ETA": "00-00 00:00",
    "HEADING": 228,
    "IMO": 0,
    "LATITUDE": 51.50719,
    "LONGITUDE": -0.07015,
    "MMSI": 244731873,
    "NAME": "GRACE",
    "NAVSTAT": 15,
    "PAC": 1,
    "ROT": 128,
    "SOG": 0.5,
    "TIME": "2024-08-23 14:27:02 GMT",
    "TYPE": 37,
    "last_seen": "2024-08-19T14:27:18.530032",
    "received_by_stations": []
  },
  "last_seen": "2024-08-23T14:27:06.454207"
}