{
  "dates_seen": [
    "2025-08-02",
    "2025-08-05"
  ],
  "last_full_data": {
    "A": 10,
    "B": 2,
    "C": 3,
    "CALLSIGN": "PI3814",
    "COG": 61.4,
    "D": 1,
    "DEST": "",
    "DRAUGHT": 0,
    "ETA": "00-00 00:00",
    "HEADING": 75,
    "IMO": 0,
    "LATITUDE": 51.50739,
    "LONGITUDE": -0.04387,
    "MMSI": 244929638,
    "NAME": "NAMANIH",
    "NAVSTAT": 15,
    "PAC": 1,
    "ROT": 128,
    "SOG": 6.2,
    "TIME": "2025-08-05 08:44:28 GMT",
    "TYPE": 37,
    "last_seen": "2025-08-05T07:36:02.282893",
    "received_by_stations": []
  },
  "last_seen": "2025-08-05T08:44:47.293138"
}