{
  "dates_seen": [
    "2025-07-24",
    "2025-07-25"
  ],
  "last_full_data": {
    "A": 48,
    "B": 1,
    "C": 4,
    "CALLSIGN": "PGNP",
    "COG": 15.3,
    "D": 3,
    "DEST": "GB LON",
    "DRAUGHT": 3,
    "ETA": "07-24 13:00",
    "HEADING": 117,
    "IMO": 5347221,
    "LATITUDE": 51.50593,
    "LONGITUDE": -0.07351,
    "MMSI": 246011000,
    "NAME": "OOSTERSCHELDE",
    "NAVSTAT": 5,
    "PAC": 0,
    "ROT": 0,
    "SOG": 0,
    "TIME": "2025-07-25 06:45:36 GMT",
    "TYPE": 0,
    "last_seen": "2025-07-25T05:39:31.351494",
    "received_by_stations": []
  },
  "last_seen": "2025-07-25T06:47:25.032397"
}