{
  "dates_seen": [
    "2025-05-11",
    "2025-05-12",
    "2025-05-25",
    "2025-05-26",
    "2025-05-27"
  ],
  "last_full_data": {
    "A": 48,
    "B": 78,
    "C": 10,
    "CALLSIGN": "CQAL8",
    "COG": 35,
    "D": 9,
    "DEST": "GB WTB > GB LON",
    "DRAUGHT": 4.8,
    "ETA": "05-25 15:00",
    "HEADING": 107,
    "IMO": 9904807,
    "LATITUDE": 51.50669,
    "LONGITUDE": -0.08086,
    "MMSI": 255806210,
    "NAME": "WORLD TRAVELLER",
    "NAVSTAT": 5,
    "PAC": 1,
    "ROT": 0,
    "SOG": 0.1,
    "TIME": "2025-05-27 09:29:33 GMT",
    "TYPE": 69,
    "last_seen": "2025-05-27T08:36:14.395172",
    "received_by_stations": []
  },
  "last_seen": "2025-05-27T09:30:19.195068"
}