{
  "dates_seen": [
    "2025-04-19",
    "2025-04-20"
  ],
  "last_full_data": {
    "A": 38,
    "B": 202,
    "C": 17,
    "CALLSIGN": "LATY8",
    "COG": 359.1,
    "D": 16,
    "DEST": "GREENWICH, UK",
    "DRAUGHT": 6.7,
    "ETA": "04-18 21:30",
    "HEADING": 94,
    "IMO": 9852432,
    "LATITUDE": 51.48416,
    "LONGITUDE": -0.01428,
    "MMSI": 257526000,
    "NAME": "VIKING VELA",
    "NAVSTAT": 5,
    "PAC": 1,
    "ROT": -5,
    "SOG": 0.1,
    "TIME": "2025-04-20 10:31:09 GMT",
    "TYPE": 69,
    "last_seen": "2025-04-20T09:25:46.952196",
    "received_by_stations": []
  },
  "last_seen": "2025-04-20T10:31:43.723254"
}