{
  "dates_seen": [
    "2025-05-01",
    "2025-05-02"
  ],
  "last_full_data": {
    "A": 19,
    "B": 106,
    "C": 11,
    "CALLSIGN": "C6EL6",
    "COG": 93.6,
    "D": 11,
    "DEST": "DKODE",
    "DRAUGHT": 5.7,
    "ETA": "05-06 03:00",
    "HEADING": 288,
    "IMO": 9842554,
    "LATITUDE": 51.50694,
    "LONGITUDE": -0.08195,
    "MMSI": 311000929,
    "NAME": "NG ENDURANCE",
    "NAVSTAT": 5,
    "PAC": 0,
    "ROT": 0,
    "SOG": 0,
    "TIME": "2025-05-02 13:32:18 GMT",
    "TYPE": 60,
    "last_seen": "2025-05-02T12:53:03.668154",
    "received_by_stations": []
  },
  "last_seen": "2025-05-02T13:35:13.999250"
}