{
  "dates_seen": [
    "2024-07-23",
    "2024-07-24",
    "2024-07-25"
  ],
  "last_full_data": {
    "A": 35,
    "B": 20,
    "C": 0,
    "CALLSIGN": "ZGPY",
    "COG": 216.5,
    "D": 0,
    "DEST": "GBLON",
    "DRAUGHT": 2.9,
    "ETA": "07-23 16:00",
    "HEADING": 126,
    "IMO": 9944950,
    "LATITUDE": 51.50366,
    "LONGITUDE": -0.07154,
    "MMSI": 319266600,
    "NAME": "IRIS BLUE",
    "NAVSTAT": 5,
    "PAC": 1,
    "ROT": 0,
    "SOG": 0,
    "TIME": "2024-07-25 01:38:32 GMT",
    "TYPE": 37,
    "last_seen": "2024-07-24T23:22:57.872683",
    "received_by_stations": []
  },
  "last_seen": "2024-07-25T01:38:38.996309"
}