{
  "dates_seen": [
    "2025-11-22",
    "2025-11-23",
    "2025-11-27",
    "2025-11-28",
    "2025-12-15",
    "2025-12-16"
  ],
  "last_full_data": {
    "A": 17,
    "B": 7,
    "C": 3,
    "CALLSIGN": "DL5014A",
    "COG": 360,
    "D": 3,
    "DEST": "",
    "DRAUGHT": 0,
    "ETA": "00-00 00:00",
    "HEADING": 167,
    "IMO": 0,
    "LATITUDE": 51.50772,
    "LONGITUDE": -0.07061,
    "MMSI": 338355609,
    "NAME": "MAY",
    "NAVSTAT": 15,
    "PAC": 1,
    "ROT": 128,
    "SOG": 0,
    "TIME": "2025-12-16 22:16:13 GMT",
    "TYPE": 37,
    "last_seen": "2025-12-16T21:16:37.315161",
    "received_by_stations": []
  },
  "last_seen": "2025-12-16T22:16:52.728720"
}