{
  "dates_seen": [
    "2025-08-01"
  ],
  "last_full_data": {
    "A": 15,
    "B": 6,
    "C": 2,
    "CALLSIGN": "",
    "COG": 268.2,
    "D": 2,
    "DEST": "LONDON .:;",
    "DRAUGHT": 0.1,
    "ETA": "06-18 12:00",
    "HEADING": 511,
    "IMO": 0,
    "LATITUDE": 51.50348,
    "LONGITUDE": -0.06624,
    "MMSI": 368424410,
    "NAME": "INEVITABLE",
    "NAVSTAT": 0,
    "PAC": 1,
    "ROT": 128,
    "SOG": 0,
    "TIME": "2025-08-01 18:45:34 GMT",
    "TYPE": 0,
    "last_seen": "2025-08-01T17:34:32.447980",
    "received_by_stations": []
  },
  "last_seen": "2025-08-01T18:45:40.661497"
}