{
  "dates_seen": [
    "2024-09-18",
    "2024-09-19"
  ],
  "last_full_data": {
    "A": 4,
    "B": 4,
    "C": 2,
    "CALLSIGN": "E5U5309",
    "COG": 14.5,
    "D": 1,
    "DEST": "",
    "DRAUGHT": 0,
    "ETA": "00-00 00:00",
    "HEADING": 511,
    "IMO": 0,
    "LATITUDE": 51.50361,
    "LONGITUDE": -0.07142,
    "MMSI": 518999328,
    "NAME": "ASTERIA TENDER",
    "NAVSTAT": 15,
    "PAC": 0,
    "ROT": 128,
    "SOG": 0.1,
    "TIME": "2024-09-19 18:30:12 GMT",
    "TYPE": 37,
    "last_seen": "2024-09-19T17:25:33.848844",
    "received_by_stations": []
  },
  "last_seen": "2024-09-19T18:32:10.415437"
}