{
  "dates_seen": [
    "2024-07-14"
  ],
  "last_full_data": {
    "A": 0,
    "B": 0,
    "C": 0,
    "CALLSIGN": "C6YZ5 2",
    "COG": 63,
    "D": 0,
    "DEST": "",
    "DRAUGHT": 0,
    "ETA": "00-00 00:00",
    "HEADING": 511,
    "IMO": 0,
    "LATITUDE": 51.48363,
    "LONGITUDE": -0.01566,
    "MMSI": 983110069,
    "NAME": "SEABOURN QUEST",
    "NAVSTAT": 15,
    "PAC": 0,
    "ROT": 128,
    "SOG": 0.6,
    "TIME": "2024-07-14 07:22:23 GMT",
    "TYPE": 53,
    "last_seen": "2024-07-14T06:32:06.804325",
    "received_by_stations": []
  },
  "last_seen": "2024-07-14T07:22:46.505833"
}